{
  "anuppuccin-theme-settings@@anp-layout-select": "anp-card-layout",
  "anuppuccin-theme-settings@@anp-hide-borders": false,
  "anuppuccin-theme-settings@@anp-card-shadows": true,
  "anuppuccin-theme-settings@@anp-card-layout-actions": true,
  "anuppuccin-theme-settings@@anp-card-layout-filebrowser": true,
  "anuppuccin-theme-settings@@ctp-custom-base@@dark": "#09041F",
  "anuppuccin-theme-settings@@anp-alt-tab-style": "anp-alternate-tab-toggle",
  "anuppuccin-theme-settings@@anp-simple-rainbow-indentation-toggle": true,
  "anuppuccin-theme-settings@@anp-simple-rainbow-collapse-toggle": true,
  "anuppuccin-theme-settings@@anp-rainbow-subfolder-color-toggle": false,
  "anuppuccin-theme-settings@@anp-collapse-folders": true,
  "anuppuccin-theme-settings@@anp-file-icons": true,
  "anuppuccin-theme-settings@@anp-file-label-align": "1",
  "anuppuccin-theme-settings@@anp-callout-select": "anp-callout-block",
  "anuppuccin-theme-settings@@list-indent": 1,
  "anuppuccin-theme-settings@@anp-table-toggle": true,
  "anuppuccin-theme-settings@@anp-table-width": true,
  "anuppuccin-theme-settings@@ctp-custom-subtext0@@dark": "#FF9D2B",
  "anuppuccin-theme-settings@@ctp-custom-surface0@@dark": "#76578A",
  "anuppuccin-theme-settings@@anp-table-auto": true,
  "anuppuccin-theme-settings@@tag-radius": 0.6,
  "anuppuccin-theme-settings@@anp-header-color-toggle": true,
  "anuppuccin-theme-settings@@ctp-custom-overlay2@@dark": "#F5E0DC",
  "anuppuccin-theme-settings@@anp-color-transition-toggle": false,
  "anuppuccin-theme-settings@@anp-full-rainbow-text-color-toggle-light": true,
  "anuppuccin-theme-settings@@anp-depth-tab-text-invert": false,
  "anuppuccin-theme-settings@@anp-editor-font-lp": "\"\"",
  "anuppuccin-theme-settings@@file-line-width": 1920,
  "anuppuccin-theme-settings-extended@@anp-theme-ext-dark": true,
  "anuppuccin-theme-settings-extended@@anp-theme-ext-light": true,
  "anuppuccin-theme-settings@@anp-codeblock-numbers": false,
  "anuppuccin-theme-settings@@anp-toggle-preview": true,
  "anuppuccin-theme-settings@@anp-kanban-hide-card-menus": false,
  "anuppuccin-theme-settings@@anp-kanban-lanes": false,
  "anuppuccin-theme-settings@@anp-print": false,
  "anuppuccin-theme-settings@@anp-button-metadata-toggle": false,
  "anuppuccin-theme-settings@@anp-autohide-titlebar": false,
  "anuppuccin-theme-settings@@anp-cursor": "pointer",
  "anuppuccin-theme-settings@@anp-canvas-dark-bg": false,
  "anuppuccin-theme-settings@@anp-rainbow-file-toggle": true,
  "anuppuccin-theme-settings@@anp-bg-fix": true,
  "anuppuccin-theme-settings-extended@@anp-theme-ext-amoled": true,
  "anuppuccin-theme-settings-extended@@catppuccin-theme-dark-extended": "ctp-dracula",
  "anuppuccin-theme-settings@@anp-callout-color-toggle": true,
  "anuppuccin-theme-settings@@anp-active-line": "anp-current-line-border",
  "anuppuccin-theme-settings@@bold-weight": "600",
  "anuppuccin-theme-settings@@anp-full-rainbow-text-color-toggle-dark": true,
  "anuppuccin-theme-settings@@anp-custom-checkboxes": true,
  "anuppuccin-theme-settings@@anuppuccin-accent-toggle": false,
  "anuppuccin-theme-settings@@anp-custom-bg-brightness-light": 0.7,
  "anuppuccin-theme-settings@@anp-floating-header": false,
  "anuppuccin-theme-settings@@anp-custom-vault-toggle": true,
  "anuppuccin-theme-settings-extended@@catppuccin-theme-extended": "ctp-gruvbox-light",
  "anuppuccin-theme-settings@@anp-background-image-toggle": true,
  "anuppuccin-theme-settings@@anp-alt-rainbow-style": "anp-simple-rainbow-color-toggle",
  "anp-custom-rainbow-colors@@rainbow-color-1-default": "rainbow-color-1-red",
  "anp-custom-rainbow-colors@@rainbow-color-3-default": "rainbow-color-3-flamingo",
  "anp-custom-rainbow-colors@@rainbow-color-4-default": "rainbow-color-4-pink",
  "anp-custom-rainbow-colors@@rainbow-color-5-default": "rainbow-color-5-green",
  "anp-custom-rainbow-colors@@rainbow-color-6-default": "rainbow-color-6-red",
  "anp-custom-rainbow-colors@@rainbow-color-9-default": "rainbow-color-9-teal",
  "anp-custom-rainbow-colors@@rainbow-color-10-default": "rainbow-color-10-blue",
  "anp-custom-rainbow-colors@@rainbow-color-11-default": "rainbow-color-11-sapphire",
  "anp-custom-rainbow-colors@@rainbow-color-2-default": "rainbow-color-2-accent",
  "anp-custom-rainbow-colors@@rainbow-color-7-default": "rainbow-color-7-maroon",
  "anuppuccin-theme-settings@@anp-toggle-metadata": false,
  "anuppuccin-theme-settings@@anp-header-divider-color-toggle": false,
  "anuppuccin-theme-settings@@anp-decoration-toggle": true,
  "anuppuccin-theme-settings@@anp-colorful-frame-icon-toggle-light": true,
  "anuppuccin-theme-settings@@anp-colorful-frame-icon-toggle-dark": true,
  "anuppuccin-theme-settings@@anp-colorful-frame-opacity": 0.5,
  "anuppuccin-theme-settings@@anp-pdf-blend-toggle-dark": true,
  "anuppuccin-theme-settings@@anp-pdf-blend-toggle-light": false,
  "anuppuccin-theme-settings@@anp-simple-rainbow-title-toggle": true,
  "anuppuccin-theme-settings@@anp-simple-rainbow-icon-toggle": false,
  "anuppuccin-theme-settings@@anp-status-bar-select": "anp-floating-status-bar",
  "anuppuccin-theme-settings@@anp-disable-newtab-align": true,
  "anuppuccin-theme-settings@@anp-depth-tab-opacity": 0.6,
  "anuppuccin-theme-settings@@anp-safari-tab-animated": true,
  "anuppuccin-theme-settings@@anp-card-radius": 40,
  "anuppuccin-theme-settings@@anp-card-header-left-padding": 10,
  "anuppuccin-theme-settings@@anp-kanban-card-opacity": 1,
  "anuppuccin-theme-settings@@callout-radius": 20,
  "anuppuccin-theme-settings@@callout-title-opacity": 0.1,
  "anuppuccin-theme-settings@@anp-speech-bubble": true,
  "anuppuccin-theme-settings@@anp-td-highlight": "none",
  "anuppuccin-theme-settings@@anp-table-highlight-opacity": 0.5,
  "anuppuccin-theme-settings@@anp-kanban-lane-radius": 6,
  "anuppuccin-theme-settings@@anp-kanban-hide-lane-border": false,
  "anuppuccin-theme-settings@@anp-safari-border-width": 2,
  "anuppuccin-theme-settings@@anp-card-layout-padding": 5,
  "anuppuccin-theme-settings@@anuppuccin-light-theme-accents": "ctp-accent-light-red",
  "anuppuccin-theme-settings@@anp-custom-bg-blur-dark": 5,
  "anuppuccin-theme-settings@@anp-custom-bg-brightness-dark": 0.7,
  "anuppuccin-theme-settings@@anp-custom-bg-card-fg-opacity-dark": 0.4,
  "anuppuccin-theme-settings@@anp-alt-tab-custom-height": 45,
  "anuppuccin-theme-settings@@anp-stacked-header-width": 35
}